CPU/Part 02/group18_lab5_part2/registers.v
//******************************************************************************************************************************//
//************************Register Module for the 8-8bit registers by Group 18 of CO224 - Lab 05 part 2*************************//
//******************************************************************************************************************************//

module reg_file(IN,OUT1,OUT2,INADDRESS,OUT1ADDRESS,OUT2ADDRESS,WRITE,CLK,RESET);//The Module

    input [7:0] IN;/*Input port "IN" is declared as a wire, this will take the input bits for the register file to write in
                    one of it's registers*/
    output  [7:0] OUT1,OUT2; /* Output ports "OUT1, OUT2" are declared as wires, these two will take the output which will 
                                contain register values specified by OUT1ADDRESS and OUT2ADDRESS respectively*/

    input [2:0] INADDRESS,OUT1ADDRESS,OUT2ADDRESS; /* Input ports "INADDRESS, OUT1ADDRESS, OUT2ADDRESS" are declared as wires
                                                    which will specify which registers to be written on/to be read from*/

    input WRITE;//this input wire will go high when writing needs to happen
    input CLK,RESET; // CLK: clock for synchronising and RESET for clearing all the registers at once

    reg [7:0] registers [7:0];// array of registers( 8,8bit registers) to work as registers in register file

//////////////////////////////////////////////////This will Clearing(Reseting) all the registers
    integer count;//count interger for the for loop
    always@(posedge CLK ) //triger this block everytime a postive edge arrises
    begin
        #1;//wait a one time unit - artificial delays to simulate the delays in a circuit
        if(RESET) begin //if RESET is high
            for(count =0;count<8;++count) begin
                registers[count] <= 8'b000_000_00;//set all the registers to zero at the end all at once
            end
        end 
    end


//////////////////////////////////////////////// This will read from registers mentioned in OUT1ADDRESS and OUT2ADDRESS
                                             /// and copy that register value to OUT1 and OUT2 respectively
    assign #2 OUT1 = registers[OUT1ADDRESS];// 2 time unis of delay to simulate circuit delays
    assign #2 OUT2 = registers[OUT2ADDRESS];// 2 time unis of delay to simulate circuit delays
    

//////////////////////////////////////////////// This will put wite to the register mentioned in INADDRESS the value in IN 
    always @(posedge CLK) // triger this block when the positive edge of the clock arises 
        begin
            #1;// 1 time uni of delay to simulate circuit delays
            if(WRITE)//if WRITE is high
            registers[INADDRESS] <= IN;//copy IN value to the register specified by INADDRESS
            
        end

    //This is to get the register values in the vcd file : Commented out for now:
    
    /* initial begin
        $dumpfile("reg_file_wavedata_G18.vcd");
        for(count=0;count<8;++count)
            $dumpvars(1,registers[count]);
    end
 */
endmodule//this is the end of the module

CPU/Part 02/group18_lab5_part2/reg_file_tb.v
// Computer Architecture (CO224) - Lab 05
// Design: Register File of Simple Processor
// Author: Kisaru Liyanage
`include "registers.v"
module reg_file_tb;
    
    reg [7:0] WRITEDATA;
    reg [2:0] WRITEREG, READREG1, READREG2;
    reg CLK, RESET, WRITEENABLE; 
    wire [7:0] REGOUT1, REGOUT2;
    
    reg_file myregfile(WRITEDATA, REGOUT1, REGOUT2, WRITEREG, READREG1, READREG2, WRITEENABLE, CLK, RESET);
       
    initial
    begin
        CLK = 1'b1;
        
        // generate files needed to plot the waveform using GTKWave
        $dumpfile("reg_file_wavedata_G18.vcd");
		$dumpvars(0, reg_file_tb);
        
        // assign values with time to input signals to see output 
        RESET = 1'b0;
        WRITEENABLE = 1'b0;
        
        #4
        RESET = 1'b1;
        READREG1 = 3'd0;
        READREG2 = 3'd4;
        
        #6
        RESET = 1'b0;
        
        #2
        WRITEREG = 3'd2;
        WRITEDATA = 8'd95;
        WRITEENABLE = 1'b1;
        
        #7
        WRITEENABLE = 1'b0;
        
        #1
        READREG1 = 3'd2;
        
        #7
        WRITEREG = 3'd1;
        WRITEDATA = 8'd28;
        WRITEENABLE = 1'b1;
        READREG1 = 3'd1;
        
        #8
        WRITEENABLE = 1'b0;
        
        #8
        WRITEREG = 3'd4;
        WRITEDATA = 8'd6;
        WRITEENABLE = 1'b1;
        
        #8
        WRITEDATA = 8'd15;
        WRITEENABLE = 1'b1;
        
        #10
        WRITEENABLE = 1'b0;
        
        #6
        WRITEREG = -3'd1;
        WRITEDATA = 8'd50;
        WRITEENABLE = 1'b1;
        
        #5
        WRITEENABLE = 1'b0;
        
        #10
        $finish;
    end
    
    // clock signal generation
    always
        #4 CLK = ~CLK;
        

endmodule

CPU/Part 02/group18_lab5_part2/reg_file_wavedata_G18.vcd
$date
	Wed Jan 12 10:03:07 2022
$end
$version
	Icarus Verilog
$end
$timescale
	1s
$end
$scope module reg_file_tb $end
$scope module myregfile $end
$var reg 8 ! \registers[0] [7:0] $end
$upscope $end
$upscope $end
$scope module reg_file_tb $end
$scope module myregfile $end
$var reg 8 " \registers[1] [7:0] $end
$upscope $end
$upscope $end
$scope module reg_file_tb $end
$scope module myregfile $end
$var reg 8 # \registers[2] [7:0] $end
$upscope $end
$upscope $end
$scope module reg_file_tb $end
$scope module myregfile $end
$var reg 8 $ \registers[3] [7:0] $end
$upscope $end
$upscope $end
$scope module reg_file_tb $end
$scope module myregfile $end
$var reg 8 % \registers[4] [7:0] $end
$upscope $end
$upscope $end
$scope module reg_file_tb $end
$scope module myregfile $end
$var reg 8 & \registers[5] [7:0] $end
$upscope $end
$upscope $end
$scope module reg_file_tb $end
$scope module myregfile $end
$var reg 8 ' \registers[6] [7:0] $end
$upscope $end
$upscope $end
$scope module reg_file_tb $end
$scope module myregfile $end
$var reg 8 ( \registers[7] [7:0] $end
$upscope $end
$upscope $end
$scope module reg_file_tb $end
$var wire 8 ) REGOUT2 [7:0] $end
$var wire 8 * REGOUT1 [7:0] $end
$var reg 1 + CLK $end
$var reg 3 , READREG1 [2:0] $end
$var reg 3 - READREG2 [2:0] $end
$var reg 1 . RESET $end
$var reg 8 / WRITEDATA [7:0] $end
$var reg 1 0 WRITEENABLE $end
$var reg 3 1 WRITEREG [2:0] $end
$scope module myregfile $end
$var wire 1 + CLK $end
$var wire 8 2 IN [7:0] $end
$var wire 3 3 INADDRESS [2:0] $end
$var wire 8 4 OUT1 [7:0] $end
$var wire 3 5 OUT1ADDRESS [2:0] $end
$var wire 8 6 OUT2 [7:0] $end
$var wire 3 7 OUT2ADDRESS [2:0] $end
$var wire 1 . RESET $end
$var wire 1 0 WRITE $end
$var integer 32 8 count [31:0] $end
$upscope $end
$upscope $end
$enddefinitions $end
#0
$dumpvars
b1000 8
bx 7
bx 6
bx 5
bx 4
bx 3
bx 2
bx 1
00
bx /
0.
bx -
bx ,
1+
bx *
bx )
bx (
bx '
bx &
bx %
bx $
bx #
bx "
bx !
$end
#4
0+
b100 -
b100 7
b0 ,
b0 5
1.
#8
1+
#9
b0 (
b0 '
b0 &
b0 %
b0 $
b0 #
b0 "
b0 !
b1000 8
#10
0.
#11
b0 )
b0 6
b0 *
b0 4
#12
10
b1011111 /
b1011111 2
b10 1
b10 3
0+
#16
1+
#17
b1011111 #
#19
00
#20
b10 ,
b10 5
0+
#22
b1011111 *
b1011111 4
#24
1+
#27
b1 ,
b1 5
10
b11100 /
b11100 2
b1 1
b1 3
#28
0+
#29
b0 *
b0 4
#32
1+
#33
b11100 "
#35
b11100 *
b11100 4
00
#36
0+
#40
1+
#43
10
b110 /
b110 2
b100 1
b100 3
#44
0+
#48
1+
#49
b110 %
#51
b110 )
b110 6
b1111 /
b1111 2
#52
0+
#56
1+
#57
b1111 %
#59
b1111 )
b1111 6
#60
0+
#61
00
#64
1+
#67
10
b110010 /
b110010 2
b111 1
b111 3
#68
0+
#72
1+
00
